README.rst
setup.py
simple_redis_lock/__init__.py
simple_redis_lock.egg-info/PKG-INFO
simple_redis_lock.egg-info/SOURCES.txt
simple_redis_lock.egg-info/dependency_links.txt
simple_redis_lock.egg-info/top_level.txt