Metadata-Version: 1.0
Name: simple-redis-lock
Version: 0.1.2
Summary: A simple redis lock.
Home-page: https://github.com/codeif/simple-redis-lock
Author: codeif
Author-email: me@codeif.com
License: MIT
Platform: UNKNOWN
